whatever.py
whatever-0.7.dist-info/LICENSE
whatever-0.7.dist-info/METADATA
whatever-0.7.dist-info/WHEEL
whatever-0.7.dist-info/pbr.json
whatever-0.7.dist-info/top_level.txt
whatever-0.7.dist-info/RECORD
